{"oid": "euskalmet/weather/regions/basque_country/zones/cantabrian_valleys/locations/lezama/forecast/trends/at/2025/05/23/for/20250523", "numericId": 0, "entityVersion": 0, "at": "2025-05-23T20:03:09Z", "for": "2025-05-23T17:50:00Z", "region": {"typeId": "summarizedRegion", "key": "euskalmet/geo/regions/basque_country", "regionId": "basque_country"}, "regionZone": {"typeId": "summarizedRegionZone", "key": "euskalmet/geo/regions/basque_country/zones/cantabrian_valleys", "regionId": "basque_country", "regionZoneId": "cantabrian_valleys"}, "regionZoneLocation": {"typeId": "summarizedRegionZoneLocation", "key": "euskalmet/geo/regions/basque_country/zones/cantabrian_valleys/locations/lezama", "regionId": "basque_country", "regionZoneId": "cantabrian_valleys", "regionZoneLocationId": "lezama"}, "trendsByDate": [{"weather": {"id": "04", "url": "https://www.euskalmet.euskadi.eus/media/assets/icons/euskalmet/webmet00-i04d.svg", "nameByLang": {"SPANISH": "Muy nuboso", "BASQUE": "Oso hodeitsu"}, "descriptionByLang": {"SPANISH": "entre 5/8 y 7/8 de cielo cubierto", "BASQUE": "zeruaren 5/8etik 7/8era estalita"}, "icon_name": "04.png", "full_path": "https://api.euskadi.eus/", "icon_name_modern": "webmet00-i04d.svg", "full_path_modern": "https://www.euskalmet.euskadi.eus/media/assets/icons/euskalmet/webmet00-i04d.svg"}, "date": "2025-05-22T22:00:00Z", "temperatureRange": {"min": 7.8, "max": 17.0, "unit": "CELSIUS_DEGREE"}}, {"weather": {"id": "04", "url": "https://www.euskalmet.euskadi.eus/media/assets/icons/euskalmet/webmet00-i04d.svg", "nameByLang": {"SPANISH": "Muy nuboso", "BASQUE": "Oso hodeitsu"}, "descriptionByLang": {"SPANISH": "entre 5/8 y 7/8 de cielo cubierto", "BASQUE": "zeruaren 5/8etik 7/8era estalita"}, "icon_name": "04.png", "full_path": "https://api.euskadi.eus/", "icon_name_modern": "webmet00-i04d.svg", "full_path_modern": "https://www.euskalmet.euskadi.eus/media/assets/icons/euskalmet/webmet00-i04d.svg"}, "date": "2025-05-25T22:00:00Z", "temperatureRange": {"min": 9.3, "max": 17.2, "unit": "CELSIUS_DEGREE"}}, {"weather": {"id": "00", "url": "https://www.euskalmet.euskadi.eus/media/assets/icons/euskalmet/webmet00-i00d.svg", "nameByLang": {"SPANISH": "Despejado", "BASQUE": "Oskarbi"}, "descriptionByLang": {"SPANISH": "cielo sin nubosidad o 1/8 de cielo cubierto", "BASQUE": "zeruan hodeirik ez edo zeruaren 1/8a estalita"}, "icon_name": "00.png", "full_path": "https://api.euskadi.eus/", "icon_name_modern": "webmet00-i00d.svg", "full_path_modern": "https://www.euskalmet.euskadi.eus/media/assets/icons/euskalmet/webmet00-i00d.svg"}, "date": "2025-05-26T22:00:00Z", "temperatureRange": {"min": 8.0, "max": 19.2, "unit": "CELSIUS_DEGREE"}}, {"weather": {"id": "00", "url": "https://www.euskalmet.euskadi.eus/media/assets/icons/euskalmet/webmet00-i00d.svg", "nameByLang": {"SPANISH": "Despejado", "BASQUE": "Oskarbi"}, "descriptionByLang": {"SPANISH": "cielo sin nubosidad o 1/8 de cielo cubierto", "BASQUE": "zeruan hodeirik ez edo zeruaren 1/8a estalita"}, "icon_name": "00.png", "full_path": "https://api.euskadi.eus/", "icon_name_modern": "webmet00-i00d.svg", "full_path_modern": "https://www.euskalmet.euskadi.eus/media/assets/icons/euskalmet/webmet00-i00d.svg"}, "date": "2025-05-27T22:00:00Z", "temperatureRange": {"min": 7.8, "max": 21.7, "unit": "CELSIUS_DEGREE"}}, {"weather": {"id": "00", "url": "https://www.euskalmet.euskadi.eus/media/assets/icons/euskalmet/webmet00-i00d.svg", "nameByLang": {"SPANISH": "Despejado", "BASQUE": "Oskarbi"}, "descriptionByLang": {"SPANISH": "cielo sin nubosidad o 1/8 de cielo cubierto", "BASQUE": "zeruan hodeirik ez edo zeruaren 1/8a estalita"}, "icon_name": "00.png", "full_path": "https://api.euskadi.eus/", "icon_name_modern": "webmet00-i00d.svg", "full_path_modern": "https://www.euskalmet.euskadi.eus/media/assets/icons/euskalmet/webmet00-i00d.svg"}, "date": "2025-05-23T22:00:00Z", "temperatureRange": {"min": 9.4, "max": 19.5, "unit": "CELSIUS_DEGREE"}}, {"weather": {"id": "00", "url": "https://www.euskalmet.euskadi.eus/media/assets/icons/euskalmet/webmet00-i00d.svg", "nameByLang": {"SPANISH": "Despejado", "BASQUE": "Oskarbi"}, "descriptionByLang": {"SPANISH": "cielo sin nubosidad o 1/8 de cielo cubierto", "BASQUE": "zeruan hodeirik ez edo zeruaren 1/8a estalita"}, "icon_name": "00.png", "full_path": "https://api.euskadi.eus/", "icon_name_modern": "webmet00-i00d.svg", "full_path_modern": "https://www.euskalmet.euskadi.eus/media/assets/icons/euskalmet/webmet00-i00d.svg"}, "date": "2025-05-24T22:00:00Z", "temperatureRange": {"min": 9.8, "max": 19.1, "unit": "CELSIUS_DEGREE"}}, {"weather": {"id": "00", "url": "https://www.euskalmet.euskadi.eus/media/assets/icons/euskalmet/webmet00-i00d.svg", "nameByLang": {"SPANISH": "Despejado", "BASQUE": "Oskarbi"}, "descriptionByLang": {"SPANISH": "cielo sin nubosidad o 1/8 de cielo cubierto", "BASQUE": "zeruan hodeirik ez edo zeruaren 1/8a estalita"}, "icon_name": "00.png", "full_path": "https://api.euskadi.eus/", "icon_name_modern": "webmet00-i00d.svg", "full_path_modern": "https://www.euskalmet.euskadi.eus/media/assets/icons/euskalmet/webmet00-i00d.svg"}, "date": "2025-05-28T22:00:00Z", "temperatureRange": {"min": 11.7, "max": 29.0, "unit": "CELSIUS_DEGREE"}}]}