{"oid": "euskalmet/weather/regions/basque_country/zones/cantabrian_valleys/locations/ormaiztegi/forecast/trends/at/2024/05/02/for/20240502", "numericId": 0, "entityVersion": 0, "at": "2024-05-02T12:03:55Z", "for": "2024-05-02T09:50:00Z", "region": {"typeId": "summarizedRegion", "key": "euskalmet/geo/regions/basque_country", "regionId": "basque_country"}, "regionZone": {"typeId": "summarizedRegionZone", "key": "euskalmet/geo/regions/basque_country/zones/cantabrian_valleys", "regionId": "basque_country", "regionZoneId": "cantabrian_valleys"}, "regionZoneLocation": {"typeId": "summarizedRegionZoneLocation", "key": "euskalmet/geo/regions/basque_country/zones/cantabrian_valleys/locations/ormaiztegi", "regionId": "basque_country", "regionZoneId": "cantabrian_valleys", "regionZoneLocationId": "ormaiztegi"}, "trendsByDate": [{"weather": {"id": "10", "path": "appcont/meteorologia/meteodat/images/10.png", "nameByLang": {"SPANISH": "Chubascos d\u00e9biles", "BASQUE": "Zaparrada txikiak"}, "descriptionByLang": {"SPANISH": "precipitaci\u00f3n intensa y de corta duraci\u00f3n, con cantidades inferiores a 15 mm/h", "BASQUE": "prezipitazio zakarra eta laburra, 15 mm/h-tik behera"}, "icon_name": "10.png", "full_path": "https://api.euskadi.eus/appcont/meteorologia/meteodat/images/10.png", "icon_name_modern": "i10d.svg", "full_path_modern": "https://www.euskalmet.euskadi.eus/meteoassets/icons/euskalmet/i10d.svg"}, "date": "2024-05-03T22:00:00Z", "temperatureRange": {"min": 12.3, "max": 15.5, "unit": "CELSIUS_DEGREE"}}, {"weather": {"id": "10", "path": "appcont/meteorologia/meteodat/images/10.png", "nameByLang": {"SPANISH": "Chubascos d\u00e9biles", "BASQUE": "Zaparrada txikiak"}, "descriptionByLang": {"SPANISH": "precipitaci\u00f3n intensa y de corta duraci\u00f3n, con cantidades inferiores a 15 mm/h", "BASQUE": "prezipitazio zakarra eta laburra, 15 mm/h-tik behera"}, "icon_name": "10.png", "full_path": "https://api.euskadi.eus/appcont/meteorologia/meteodat/images/10.png", "icon_name_modern": "i10d.svg", "full_path_modern": "https://www.euskalmet.euskadi.eus/meteoassets/icons/euskalmet/i10d.svg"}, "date": "2024-05-04T22:00:00Z", "temperatureRange": {"min": 11.3, "max": 15.2, "unit": "CELSIUS_DEGREE"}}, {"weather": {"id": "10", "path": "appcont/meteorologia/meteodat/images/10.png", "nameByLang": {"SPANISH": "Chubascos d\u00e9biles", "BASQUE": "Zaparrada txikiak"}, "descriptionByLang": {"SPANISH": "precipitaci\u00f3n intensa y de corta duraci\u00f3n, con cantidades inferiores a 15 mm/h", "BASQUE": "prezipitazio zakarra eta laburra, 15 mm/h-tik behera"}, "icon_name": "10.png", "full_path": "https://api.euskadi.eus/appcont/meteorologia/meteodat/images/10.png", "icon_name_modern": "i10d.svg", "full_path_modern": "https://www.euskalmet.euskadi.eus/meteoassets/icons/euskalmet/i10d.svg"}, "date": "2024-05-01T22:00:00Z", "temperatureRange": {"min": 4.0, "max": 12.6, "unit": "CELSIUS_DEGREE"}}, {"weather": {"id": "10", "path": "appcont/meteorologia/meteodat/images/10.png", "nameByLang": {"SPANISH": "Chubascos d\u00e9biles", "BASQUE": "Zaparrada txikiak"}, "descriptionByLang": {"SPANISH": "precipitaci\u00f3n intensa y de corta duraci\u00f3n, con cantidades inferiores a 15 mm/h", "BASQUE": "prezipitazio zakarra eta laburra, 15 mm/h-tik behera"}, "icon_name": "10.png", "full_path": "https://api.euskadi.eus/appcont/meteorologia/meteodat/images/10.png", "icon_name_modern": "i10d.svg", "full_path_modern": "https://www.euskalmet.euskadi.eus/meteoassets/icons/euskalmet/i10d.svg"}, "date": "2024-05-02T22:00:00Z", "temperatureRange": {"min": 6.1, "max": 14.8, "unit": "CELSIUS_DEGREE"}}, {"weather": {"id": "01", "path": "appcont/meteorologia/meteodat/images/01.png", "nameByLang": {"SPANISH": "Poco nuboso", "BASQUE": "Hodei gutxi"}, "descriptionByLang": {"SPANISH": "entre 1/8 y 2/8 de cielo cubierto", "BASQUE": "zeruaren 1/8etik 2/8era estalita"}, "icon_name": "01.png", "full_path": "https://api.euskadi.eus/appcont/meteorologia/meteodat/images/01.png", "icon_name_modern": "i01d.svg", "full_path_modern": "https://www.euskalmet.euskadi.eus/meteoassets/icons/euskalmet/i01d.svg"}, "date": "2024-05-07T22:00:00Z", "temperatureRange": {"min": 3.4, "max": 15.3, "unit": "CELSIUS_DEGREE"}}, {"weather": {"id": "12", "path": "appcont/meteorologia/meteodat/images/12.png", "nameByLang": {"SPANISH": "Lluvia d\u00e9bil", "BASQUE": "Euri txikia"}, "descriptionByLang": {"SPANISH": "precipitaci\u00f3n de agua l\u00edquida, con cantidades inferiores a 15 mm/h", "BASQUE": "ur likidozko prezipitazioa, 15 mm/h-tik behera"}, "icon_name": "12.png", "full_path": "https://api.euskadi.eus/appcont/meteorologia/meteodat/images/12.png", "icon_name_modern": "i12d.svg", "full_path_modern": "https://www.euskalmet.euskadi.eus/meteoassets/icons/euskalmet/i12d.svg"}, "date": "2024-05-05T22:00:00Z", "temperatureRange": {"min": 6.7, "max": 11.9, "unit": "CELSIUS_DEGREE"}}, {"weather": {"id": "12", "path": "appcont/meteorologia/meteodat/images/12.png", "nameByLang": {"SPANISH": "Lluvia d\u00e9bil", "BASQUE": "Euri txikia"}, "descriptionByLang": {"SPANISH": "precipitaci\u00f3n de agua l\u00edquida, con cantidades inferiores a 15 mm/h", "BASQUE": "ur likidozko prezipitazioa, 15 mm/h-tik behera"}, "icon_name": "12.png", "full_path": "https://api.euskadi.eus/appcont/meteorologia/meteodat/images/12.png", "icon_name_modern": "i12d.svg", "full_path_modern": "https://www.euskalmet.euskadi.eus/meteoassets/icons/euskalmet/i12d.svg"}, "date": "2024-05-06T22:00:00Z", "temperatureRange": {"min": 3.9, "max": 11.8, "unit": "CELSIUS_DEGREE"}}]}